vennfan/__init__.py
vennfan/colors.py
vennfan/curves.py
vennfan/utils.py
vennfan/vennfan.py
vennfan/vennfan_defaults.yaml
vennfan/venntrig.py
vennfan/venntrig_defaults.yaml
vennfan-0.0.6.dist-info/licenses/LICENSE
vennfan-0.0.6.dist-info/METADATA
vennfan-0.0.6.dist-info/WHEEL
vennfan-0.0.6.dist-info/top_level.txt
vennfan-0.0.6.dist-info/RECORD
