Metadata-Version: 2.4
Name: vennfan
Version: 0.0.6
Summary: VennFan
Author-email: Bálint Csanády <csbalint@protonmail.ch>
License-Expression: MIT
Project-URL: Repository, https://github.com/aielte-research/vennfan.git
Project-URL: arXiv, https://arxiv.org/abs/2601.06980
Keywords: Venn,Venn diagram,Matplotlib,6 sets,7 sets,8 sets,visualization,plotting
Classifier: Programming Language :: Python :: 3 :: Only
Classifier: Programming Language :: Python :: 3.9
Classifier: Programming Language :: Python :: 3.10
Classifier: Programming Language :: Python :: 3.11
Classifier: Programming Language :: Python :: 3.12
Classifier: Framework :: Matplotlib
Classifier: Operating System :: OS Independent
Classifier: Topic :: Scientific/Engineering :: Mathematics
Classifier: Topic :: Scientific/Engineering :: Visualization
Requires-Python: >=3.9
License-File: LICENSE
Requires-Dist: numpy
Requires-Dist: matplotlib
Requires-Dist: pyyaml
Requires-Dist: scipy
Dynamic: license-file
